distancerasters/__init__.py
distancerasters/main.py
distancerasters/utils.py
distancerasters-0.3.3.dist-info/LICENSE.txt
distancerasters-0.3.3.dist-info/METADATA
distancerasters-0.3.3.dist-info/WHEEL
distancerasters-0.3.3.dist-info/top_level.txt
distancerasters-0.3.3.dist-info/RECORD
