Metadata-Version: 2.1
Name: distancerasters
Version: 0.3.3
Summary: Generate distance raster using arbitrary sets of spatial features
Home-page: https://github.com/sgoodm/python-distance-rasters
Author: Seth Goodman
Author-email: sgoodman@aiddata.wm.edu
License: BSD 3-Clause License
Project-URL: Bug Tracker, https://github.com/sgoodm/python-distance-rasters/issues
Keywords: raster,distance,spatial
Classifier: Programming Language :: Python :: 3
License-File: LICENSE.txt
Requires-Dist: numpy
Requires-Dist: rasterio
Requires-Dist: fiona
Requires-Dist: affine
Requires-Dist: scipy >=1.6.0
Requires-Dist: rasterstats
Requires-Dist: tqdm
